[
  {
    "region": "apac",
    "service": "support",
    "latency_ms": 140.45,
    "uptime_pct": 98.185,
    "timestamp": 20250301
  },
  {
    "region": "apac",
    "service": "recommendations",
    "latency_ms": 134.6,
    "uptime_pct": 97.399,
    "timestamp": 20250302
  },
  {
    "region": "apac",
    "service": "analytics",
    "latency_ms": 122.79,
    "uptime_pct": 98.659,
    "timestamp": 20250303
  },
  {
    "region": "apac",
    "service": "checkout",
    "latency_ms": 111.85,
    "uptime_pct": 99.142,
    "timestamp": 20250304
  },
  {
    "region": "apac",
    "service": "support",
    "latency_ms": 161.04,
    "uptime_pct": 98.534,
    "timestamp": 20250305
  },
  {
    "region": "apac",
    "service": "checkout",
    "latency_ms": 162.99,
    "uptime_pct": 98.116,
    "timestamp": 20250306
  },
  {
    "region": "apac",
    "service": "support",
    "latency_ms": 202.31,
    "uptime_pct": 97.278,
    "timestamp": 20250307
  },
  {
    "region": "apac",
    "service": "checkout",
    "latency_ms": 144.05,
    "uptime_pct": 97.107,
    "timestamp": 20250308
  },
  {
    "region": "apac",
    "service": "support",
    "latency_ms": 186.61,
    "uptime_pct": 99.367,
    "timestamp": 20250309
  },
  {
    "region": "apac",
    "service": "analytics",
    "latency_ms": 147.05,
    "uptime_pct": 97.528,
    "timestamp": 20250310
  },
  {
    "region": "apac",
    "service": "payments",
    "latency_ms": 154.36,
    "uptime_pct": 98.259,
    "timestamp": 20250311
  },
  {
    "region": "apac",
    "service": "recommendations",
    "latency_ms": 135.87,
    "uptime_pct": 99.085,
    "timestamp": 20250312
  },
  {
    "region": "emea",
    "service": "recommendations",
    "latency_ms": 130.2,
    "uptime_pct": 98.129,
    "timestamp": 20250301
  },
  {
    "region": "emea",
    "service": "checkout",
    "latency_ms": 216.78,
    "uptime_pct": 99.435,
    "timestamp": 20250302
  },
  {
    "region": "emea",
    "service": "analytics",
    "latency_ms": 216.06,
    "uptime_pct": 97.862,
    "timestamp": 20250303
  },
  {
    "region": "emea",
    "service": "recommendations",
    "latency_ms": 194.76,
    "uptime_pct": 99,
    "timestamp": 20250304
  },
  {
    "region": "emea",
    "service": "payments",
    "latency_ms": 173.37,
    "uptime_pct": 97.902,
    "timestamp": 20250305
  },
  {
    "region": "emea",
    "service": "support",
    "latency_ms": 217.18,
    "uptime_pct": 98.929,
    "timestamp": 20250306
  },
  {
    "region": "emea",
    "service": "support",
    "latency_ms": 198.5,
    "uptime_pct": 97.235,
    "timestamp": 20250307
  },
  {
    "region": "emea",
    "service": "checkout",
    "latency_ms": 117.39,
    "uptime_pct": 98.477,
    "timestamp": 20250308
  },
  {
    "region": "emea",
    "service": "analytics",
    "latency_ms": 211.17,
    "uptime_pct": 98.376,
    "timestamp": 20250309
  },
  {
    "region": "emea",
    "service": "payments",
    "latency_ms": 111.16,
    "uptime_pct": 98.943,
    "timestamp": 20250310
  },
  {
    "region": "emea",
    "service": "recommendations",
    "latency_ms": 237.59,
    "uptime_pct": 97.679,
    "timestamp": 20250311
  },
  {
    "region": "emea",
    "service": "payments",
    "latency_ms": 138.49,
    "uptime_pct": 99.061,
    "timestamp": 20250312
  },
  {
    "region": "amer",
    "service": "catalog",
    "latency_ms": 190.21,
    "uptime_pct": 97.962,
    "timestamp": 20250301
  },
  {
    "region": "amer",
    "service": "payments",
    "latency_ms": 118.58,
    "uptime_pct": 98.698,
    "timestamp": 20250302
  },
  {
    "region": "amer",
    "service": "payments",
    "latency_ms": 125.25,
    "uptime_pct": 98.599,
    "timestamp": 20250303
  },
  {
    "region": "amer",
    "service": "catalog",
    "latency_ms": 221.3,
    "uptime_pct": 98.927,
    "timestamp": 20250304
  },
  {
    "region": "amer",
    "service": "catalog",
    "latency_ms": 159.79,
    "uptime_pct": 99.404,
    "timestamp": 20250305
  },
  {
    "region": "amer",
    "service": "support",
    "latency_ms": 150.61,
    "uptime_pct": 98.237,
    "timestamp": 20250306
  },
  {
    "region": "amer",
    "service": "analytics",
    "latency_ms": 175.16,
    "uptime_pct": 97.378,
    "timestamp": 20250307
  },
  {
    "region": "amer",
    "service": "analytics",
    "latency_ms": 141.01,
    "uptime_pct": 98.577,
    "timestamp": 20250308
  },
  {
    "region": "amer",
    "service": "recommendations",
    "latency_ms": 140.86,
    "uptime_pct": 99.388,
    "timestamp": 20250309
  },
  {
    "region": "amer",
    "service": "analytics",
    "latency_ms": 143.01,
    "uptime_pct": 97.692,
    "timestamp": 20250310
  },
  {
    "region": "amer",
    "service": "payments",
    "latency_ms": 110.21,
    "uptime_pct": 97.694,
    "timestamp": 20250311
  },
  {
    "region": "amer",
    "service": "checkout",
    "latency_ms": 203.18,
    "uptime_pct": 97.487,
    "timestamp": 20250312
  }
]